zeversolarlocal/__init__.py
zeversolarlocal/__main__.py
zeversolarlocal/api.py
zeversolarlocal/cli.py
zeversolarlocal/py.typed
zeversolarlocal-1.1.0.dist-info/WHEEL
zeversolarlocal-1.1.0.dist-info/METADATA
zeversolarlocal-1.1.0.dist-info/RECORD
