Metadata-Version: 2.1
Name: zeversolarlocal
Version: 1.1.0
Summary: zeversolarlocal
Home-page: https://github.com/sander76/zeversolarlocal
Keywords: solar,async,energy
Author: Sander Teunissen
Requires-Python: >=3.7
Classifier: License :: OSI Approved :: MIT License
Classifier: Intended Audience :: Developers
Classifier: Programming Language :: Python :: 3
Classifier: Topic :: Software Development :: Libraries :: Python Modules
Requires-Dist: httpx
Requires-Dist: pylint ; extra == "dev"
Requires-Dist: nox ; extra == "dev"
Requires-Dist: pytest-cov ; extra == "dev"
Requires-Dist: coverage[toml]>=5.0.3 ; extra == "dev"
Requires-Dist: pre-commit ; extra == "dev"
Requires-Dist: pytest ; extra == "test"
Requires-Dist: pytest-asyncio ; extra == "test"
Requires-Dist: pytest-mock ; extra == "test"
Provides-Extra: dev
Provides-Extra: test
